relecov_tools/__init__.py
relecov_tools/__main__.py
relecov_tools/base_module.py
relecov_tools/build_schema.py
relecov_tools/config_json.py
relecov_tools/download.py
relecov_tools/ena_upload.py
relecov_tools/gisaid_upload.py
relecov_tools/log_summary.py
relecov_tools/mail.py
relecov_tools/map.py
relecov_tools/metadata_homogeneizer.py
relecov_tools/pipeline_manager.py
relecov_tools/read_bioinfo_metadata.py
relecov_tools/read_lab_metadata.py
relecov_tools/rest_api.py
relecov_tools/sftp_client.py
relecov_tools/upload_database.py
relecov_tools/upload_results.py
relecov_tools/utils.py
relecov_tools/validate.py
relecov_tools/wrapper.py
relecov_tools/assets/Relecov_metadata_template_v3.2.3.xlsx
relecov_tools/assets/compare_sampleids.sh
relecov_tools/assets/ena_templates/ENA.project.xsd
relecov_tools/assets/ena_templates/ENA_template_FILE.xml
relecov_tools/assets/ena_templates/ENA_template_LIBRARY_SELECTION.xml
relecov_tools/assets/ena_templates/ENA_template_LIBRARY_SOURCE.xml
relecov_tools/assets/ena_templates/ENA_template_LIBRARY_STRATEGY.xml
relecov_tools/assets/ena_templates/ENA_template_PLATFORM.xml
relecov_tools/assets/ena_templates/ENA_template_experiments.xml
relecov_tools/assets/ena_templates/ENA_template_runs.xml
relecov_tools/assets/ena_templates/ENA_template_samples_ERC000011.xml
relecov_tools/assets/ena_templates/ENA_template_samples_ERC000012.xml
relecov_tools/assets/ena_templates/ENA_template_samples_ERC000013.xml
relecov_tools/assets/ena_templates/ENA_template_samples_ERC000014.xml
relecov_tools/assets/ena_templates/ENA_template_samples_ERC000015.xml
relecov_tools/assets/ena_templates/ENA_template_samples_ERC000016.xml
relecov_tools/assets/ena_templates/ENA_template_samples_ERC000017.xml
relecov_tools/assets/ena_templates/ENA_template_samples_ERC000018.xml
relecov_tools/assets/ena_templates/ENA_template_samples_ERC000019.xml
relecov_tools/assets/ena_templates/ENA_template_samples_ERC000020.xml
relecov_tools-1.7.4.dist-info/licenses/LICENSE
relecov_tools-1.7.4.dist-info/METADATA
relecov_tools-1.7.4.dist-info/WHEEL
relecov_tools-1.7.4.dist-info/entry_points.txt
relecov_tools-1.7.4.dist-info/top_level.txt
relecov_tools-1.7.4.dist-info/RECORD
