Metadata-Version: 2.4
Name: relecov-tools
Version: 1.7.4
Summary: Tools for managing and proccessing relecov network data.
Author-email: Sara Monzon <smonzon@isciii.es>, Luis Chapado <lchapado@externos.isciii.es>, Isabel Cuesta <isabel.cuesta@isciii.es>, Sarai Varona <s.varona@isciii.es>, Daniel Valle <da.valle@externos.isciii.es>, Pablo Mata <pmata@externos.isciii.es>, Victor Lopez <vmlopez@isciii.es>, Emi Arjona <eiarjona@isciii.es>, Jaime Ozaez <jaime.ozaez@isciii.es>, Juan Ledesma <juan.ledesma@isciii.es>, Sergio Olmos <sergio.olmos@externos.isciii.es>, Alejandro Bernabeu <abernabeu@isciii.es>, Alba Talavera <al
Maintainer-email: Sara Monzon <smonzon@isciii.es>, Luis Chapado <lchapado@externos.isciii.es>, Isabel Cuesta <isabel.cuesta@isciii.es>, Sarai Varona <s.varona@isciii.es>, Daniel Valle <da.valle@externos.isciii.es>, Pablo Mata <pmata@externos.isciii.es>, Victor Lopez <vmlopez@isciii.es>, Emi Arjona <eiarjona@isciii.es>, Jaime Ozaez <jaime.ozaez@isciii.es>, Juan Ledesma <juan.ledesma@isciii.es>, Sergio Olmos <sergio.olmos@externos.isciii.es>, Alejandro Bernabeu <abernabeu@isciii.es>, Alba Talavera
License: GNU GENERAL PUBLIC LICENSE v.3
Project-URL: Homepage, https://github.com/BU-ISCIII/relecov-tools
Keywords: relecov,bioinformatics,pipeline,sequencing,NGS,next generation sequencing
Requires-Python: >=3.10
License-File: LICENSE
Requires-Dist: click
Requires-Dist: questionary
Requires-Dist: jsonschema
Requires-Dist: packaging
Requires-Dist: prompt_toolkit>=3.0.3
Requires-Dist: rich>=10.0.0
Requires-Dist: requests==2.27.1
Requires-Dist: paramiko>=2.10.1
Requires-Dist: pyyaml==6.0.1
Requires-Dist: openpyxl>=3.1.2
Requires-Dist: ena-upload-cli
Requires-Dist: bio==1.4.0
Requires-Dist: xlsxwriter==3.2.0
Requires-Dist: bs4==0.0.2
Requires-Dist: tabulate
Requires-Dist: pandas
Requires-Dist: jinja2>=3.0.0
Requires-Dist: semantic_version
Requires-Dist: geopy
Dynamic: license-file
